MANIFEST.in
Makefile
README
gitscob.py
mangler.py
setup.py
test/__init__.py
test/__init__.pyc
test/test_example.py
test/test_example.pyc
tiddlywebplugins/__init__.py
tiddlywebplugins/geofilters.py
tiddlywebplugins.geofilters.egg-info/PKG-INFO
tiddlywebplugins.geofilters.egg-info/SOURCES.txt
tiddlywebplugins.geofilters.egg-info/dependency_links.txt
tiddlywebplugins.geofilters.egg-info/namespace_packages.txt
tiddlywebplugins.geofilters.egg-info/not-zip-safe
tiddlywebplugins.geofilters.egg-info/requires.txt
tiddlywebplugins.geofilters.egg-info/top_level.txt