Metadata-Version: 1.0
Name: tiddlywebplugins.geofilters
Version: 0.931
Summary: Provides new filter near=lat,long,radius to allow queries against geo tiddlers (tiddlers with geo.long and geo.lat fields)
Home-page: http://pypi.python.org/pypi/tiddlywebplugins.geofilters
Author: Jon Robson
Author-email: jdlrobson@gmail.com
License: UNKNOWN
Platform: Posix; MacOS X; Windows
